README.rst
setup.py
chain/__init__.py
chain/client.py
chain_py.egg-info/PKG-INFO
chain_py.egg-info/SOURCES.txt
chain_py.egg-info/dependency_links.txt
chain_py.egg-info/requires.txt
chain_py.egg-info/top_level.txt
tests/__init__.py
tests/test_client.py