Metadata-Version: 1.1
Name: chain-py
Version: 0.1.7
Summary: An expressive clean way to interact with RESTful APIs.
Home-page: https://github.com/ajpen/chain
Author: Anfernee Jervis
Author-email: anferneejervis@gmail.com
License: UNKNOWN
Platform: UNKNOWN
Classifier: Development Status :: 2 - Pre-Alpha
Classifier: Programming Language :: Python
Classifier: Programming Language :: Python :: 2
Classifier: Programming Language :: Python :: 2.7
Classifier: Programming Language :: Python :: 3
Classifier: Programming Language :: Python :: 3.4
Classifier: Programming Language :: Python :: 3.5
